odoo9_addon_business_requirement_deliverable-9.0.1.0.0.99.dev7-py2.7-nspkg.pth
odoo_addons/business_requirement_deliverable/__openerp__.py
odoo_addons/business_requirement_deliverable/__init__.py
odoo_addons/business_requirement_deliverable/README.rst
odoo_addons/business_requirement_deliverable/security/ir.model.access.csv
odoo_addons/business_requirement_deliverable/models/business.py
odoo_addons/business_requirement_deliverable/models/__init__.py
odoo_addons/business_requirement_deliverable/views/business_view.xml
odoo_addons/business_requirement_deliverable/tests/__init__.py
odoo_addons/business_requirement_deliverable/tests/test_br.py
odoo_addons/business_requirement_deliverable/static/img/bus_req_deliverable2.png
odoo_addons/business_requirement_deliverable/static/img/bus_req_resource.png
odoo_addons/business_requirement_deliverable/static/img/bus_req_deliverable.png
odoo_addons/business_requirement_deliverable/static/description/icon.png
odoo9_addon_business_requirement_deliverable-9.0.1.0.0.99.dev7.dist-info/top_level.txt
odoo9_addon_business_requirement_deliverable-9.0.1.0.0.99.dev7.dist-info/WHEEL
odoo9_addon_business_requirement_deliverable-9.0.1.0.0.99.dev7.dist-info/RECORD
odoo9_addon_business_requirement_deliverable-9.0.1.0.0.99.dev7.dist-info/metadata.json
odoo9_addon_business_requirement_deliverable-9.0.1.0.0.99.dev7.dist-info/DESCRIPTION.rst
odoo9_addon_business_requirement_deliverable-9.0.1.0.0.99.dev7.dist-info/METADATA
odoo9_addon_business_requirement_deliverable-9.0.1.0.0.99.dev7.dist-info/namespace_packages.txt
